excel_generator/__init__.py
excel_generator/__main__.py
excel_generator/cli_constants.py
excel_generator/env_constants.py
excel_generator/env_startup.py
excel_generator/environment.py
excel_generator/generator.py
excel_generator/io_utils.py
excel_generator-1.0.2.dist-info/LICENSE
excel_generator-1.0.2.dist-info/METADATA
excel_generator-1.0.2.dist-info/WHEEL
excel_generator-1.0.2.dist-info/top_level.txt
excel_generator-1.0.2.dist-info/RECORD
