Metadata-Version: 2.1
Name: excel-generator
Version: 1.0.2
Summary: An excel generator that takes as input a JSON file. The format of the file is list of dictionaries.
Home-page: https://github.com/estuaryoss/test-libs-python/tree/master/excel_generator
Author: Catalin Dinuta
Author-email: constantin.dinuta@gmail.com
License: Apache
Platform: UNKNOWN
Classifier: Programming Language :: Python :: 3.7
Classifier: Programming Language :: Python :: 3.8
Classifier: Programming Language :: Python :: 3.9
Classifier: License :: OSI Approved :: Apache Software License
Classifier: Operating System :: OS Independent
Requires-Dist: click
Requires-Dist: pyexcel
Requires-Dist: pyexcel-xls
Requires-Dist: pyexcel-xlsx
Requires-Dist: pyexcel-xlsxw
Requires-Dist: setuptools (==44.0.0)
Requires-Dist: jproperties
